paic_patterns/__init__.py
paic_patterns/main.py
paic_patterns/py.typed
paic_patterns/commands/__init__.py
paic_patterns/commands/member_commands.py
paic_patterns/commands/spec_commands.py
paic_patterns/modules/__init__.py
paic_patterns/modules/aider_llm_models.py
paic_patterns/modules/data_types.py
paic_patterns/modules/director_intelligence.py
paic_patterns/modules/logging.py
paic_patterns/modules/member_runner.py
paic_patterns/modules/spec_director_runner.py
paic_patterns/modules/spec_module.py
paic_patterns/modules/spec_runner.py
paic_patterns/modules/spec_templates.py
paic_patterns/modules/summarize.py
paic_patterns/modules/versioning.py
paic_patterns/tests/__init__.py
paic_patterns/tests/director_intelligence_test.py
paic_patterns/tests/logging_test.py
paic_patterns/tests/member_runner_test.py
paic_patterns/tests/paic_patterns_essentials_test.py
paic_patterns/tests/pattern_templates_to_docs_test.py
paic_patterns/tests/spec_director_runner_test.py
paic_patterns/tests/spec_format_tests.py
paic_patterns/tests/spec_module_test.py
paic_patterns/tests/spec_runner_test.py
paic_patterns/tests/spec_templates_test.py
paic_patterns/tests/summarizer_test.py
paic_patterns/tests/versioning_test.py
paic_patterns-0.1.53.dist-info/METADATA
paic_patterns-0.1.53.dist-info/WHEEL
paic_patterns-0.1.53.dist-info/entry_points.txt
paic_patterns-0.1.53.dist-info/RECORD
