Metadata-Version: 2.4
Name: paic-patterns
Version: 0.1.53
Summary: Principled AI Coding Patterns for large-scale, max-compute, low-error engineering in the GenAI Age.
Author-email: indydevdan <dan@agenticengineer.com>
Requires-Python: <3.13,>=3.9
Requires-Dist: aider-chat==0.75.1
Requires-Dist: pydantic>=2.10.5
Requires-Dist: pytest>=8.3.4
Requires-Dist: python-dotenv>=1.0.1
Requires-Dist: pyyaml>=6.0.2
Requires-Dist: rich>=13.9.4
Requires-Dist: typer>=0.15.1
